annotated/__init__.py
annotated/annotated.py
annotated-0.0.2.dist-info/DESCRIPTION.rst
annotated-0.0.2.dist-info/METADATA
annotated-0.0.2.dist-info/RECORD
annotated-0.0.2.dist-info/WHEEL
annotated-0.0.2.dist-info/metadata.json
annotated-0.0.2.dist-info/top_level.txt
