Metadata-Version: 1.1
Name: annotated
Version: 0.0.2
Summary: Apply annotations as callables on their respective arguments
Home-page: https://github.com/WhatNodyn/Annotate
Author: Neil Cecchini
Author-email: stranger.neil@gmail.com
License: MIT
Keywords: annotations decorator function development
Platform: UNKNOWN
Classifier: Development Status :: 3 - Alpha
Classifier: Intended Audience :: Developers
Classifier: Topic :: Software Development :: Libraries
Classifier: Programming Language :: Python :: 3 :: Only
Classifier: License :: OSI Approved :: MIT License
